proxyport2/__init__.py
proxyport2/__main__.py
proxyport2/__version__.py
proxyport2/proxyport2.py
proxyport2-1.1.0.dist-info/LICENSE
proxyport2-1.1.0.dist-info/METADATA
proxyport2-1.1.0.dist-info/WHEEL
proxyport2-1.1.0.dist-info/top_level.txt
proxyport2-1.1.0.dist-info/RECORD
